nbnorm/__init__.py
nbnorm/nbnorm.py
nbnorm/version.py
nbnorm/xpath.py
nbnorm-0.6.2.dist-info/METADATA
nbnorm-0.6.2.dist-info/WHEEL
nbnorm-0.6.2.dist-info/entry_points.txt
nbnorm-0.6.2.dist-info/RECORD
