Metadata-Version: 2.4
Name: nbnorm
Version: 0.6.2
Summary: convenience tool to do mass notebook normalization.
Project-URL: Repository, https://github.com/flotpython/nbnorm
Project-URL: Bug Tracker, https://github.com/flotpython/nbnorm/issues
Project-URL: Changelog, https://github.com/flotpython/nbnorm/blob/main/CHANGELOG.md
Author-email: Thierry Parmentelat <thierry.parmentelat@minesparis.psl.eu>
License: MIT License
Keywords: education,jupyter,notebook,teaching
Requires-Python: >=3.8
Requires-Dist: jupytext
